dottmi/__init__.py
dottmi/breakpoint.py
dottmi/breakpointhandler.py
dottmi/dott.py
dottmi/dottexceptions.py
dottmi/fixtures.py
dottmi/gdb.py
dottmi/gdb_cmds.py
dottmi/gdb_mi.py
dottmi/gdb_shared.py
dottmi/gdbcontrollerdott.py
dottmi/pylinkdott.py
dottmi/symbols.py
dottmi/target.py
dottmi/target_mem.py
dottmi/utils.py
ams_dott-1.6.4.post1.dist-info/LICENSE.txt
ams_dott-1.6.4.post1.dist-info/METADATA
ams_dott-1.6.4.post1.dist-info/WHEEL
ams_dott-1.6.4.post1.dist-info/top_level.txt
ams_dott-1.6.4.post1.dist-info/RECORD
