Metadata-Version: 2.1
Name: ams-dott
Version: 1.6.4.post1
Summary: Debugger-based on Target Testing (DOTT)
Home-page: https://github.com/twinkler-ams-osram/dott
Author: Thomas Winkler
Author-email: thomas.winkler@ams.com
License: UNKNOWN
Platform: UNKNOWN
Classifier: Environment :: Console
Classifier: License :: OSI Approved :: Apache Software License
Classifier: Topic :: Software Development :: Testing
Classifier: Topic :: Software Development :: Debuggers
Classifier: Topic :: Software Development :: Embedded Systems
Requires-Python: >=3.6
Requires-Dist: ams-dott-runtime (==1.1.0)
Requires-Dist: pygdbmi (==0.10.0.1)
Requires-Dist: pylink-square (==0.11.1)
Requires-Dist: pytest
Requires-Dist: pytest-cov
Requires-Dist: pytest-instafail
Requires-Dist: pytest-repeat
Requires-Dist: pyserial
Requires-Dist: pigpio
Requires-Dist: matplotlib
